webexcortex/__init__.py
webexcortex/__main__.py
webexcortex/client.py
webexcortex/datatypes.py
webexcortex/handler.py
webexcortex/main.py
webexcortex/responder.py
webex_cortex-1.0.1.dist-info/LICENSE
webex_cortex-1.0.1.dist-info/METADATA
webex_cortex-1.0.1.dist-info/WHEEL
webex_cortex-1.0.1.dist-info/entry_points.txt
webex_cortex-1.0.1.dist-info/top_level.txt
webex_cortex-1.0.1.dist-info/RECORD
